
<ObjectSpec>
<SpecVersion>17_0_11-163677</SpecVersion>
<Object>
<ObjClsGuid>1db606f2-af09-4cf9-a3b5-b481519d28f6</ObjClsGuid>
<ObjCls>0</ObjCls>
<ObjId>25</ObjId>
<ObjName>Empresa</ObjName>
<ObjDesc>Empresa</ObjDesc>
<ObjPgmName>Empresa</ObjPgmName>
<ObjClsName>Transaction</ObjClsName></Object>
<Result>genreq</Result>
<Warnings></Warnings>
<Errors></Errors>
<Generator>
<GenId>12</GenId>
<GenName>Default (Java)</GenName></Generator>
<FormClass>HTML</FormClass>
<Parameters>
<Parameter>
<IO>in</IO>
<Variable>
<VarId>Mode</VarId>
<VarName>&amp;Mode</VarName></Variable></Parameter>
<Parameter>
<IO>in</IO>
<Variable>
<VarId>Empresaid</VarId>
<VarName>&amp;EmpresaId</VarName></Variable></Parameter></Parameters>
<Levels>
<Level>
<LevelType>Trn</LevelType>
<LevelNumber>26</LevelNumber>
<BaseTable>
<Table>
<TableId>26</TableId>
<TableName>Empresa</TableName>
<Description>Empresa</Description></Table></BaseTable>
<NavigationTree>
<Table>
<TableId>26</TableId>
<TableName>Empresa</TableName>
<Description>Empresa</Description>
<Updated>Yes</Updated>
<RecordsToRead>many</RecordsToRead>
<KeyAttributes>
<Attribute>
<AttriId>28</AttriId>
<AttriName>EmpresaId</AttriName>
<Description>Empresa Id</Description></Attribute></KeyAttributes>
<Tables></Tables></Table></NavigationTree>
<Formulas>
<VerticalFormulas></VerticalFormulas>
<AggSelFormulas></AggSelFormulas></Formulas>
<DynamicLoads></DynamicLoads>
<Rules></Rules>
<AfterAttributeRules></AfterAttributeRules>
<AfterConfirmRules></AfterConfirmRules>
<TablesToUpdate>
<TableToUpdate>
<Table>
<TableId>26</TableId>
<TableName>Empresa</TableName>
<Description>Empresa</Description></Table>
<TableAction>insert</TableAction>
<AttrisToUpdate>
<Attribute>
<AttriId>28</AttriId>
<AttriName>EmpresaId</AttriName>
<Description>Empresa Id</Description></Attribute>
<Attribute>
<AttriId>121</AttriId>
<AttriName>EmpresaNombre</AttriName>
<Description>Empresa Nombre</Description></Attribute>
<Attribute>
<AttriId>122</AttriId>
<AttriName>EmpresaDireccion</AttriName>
<Description>Empresa Direccion</Description></Attribute>
<Attribute>
<AttriId>123</AttriId>
<AttriName>EmpresaRuc</AttriName>
<Description>Empresa Ruc</Description></Attribute>
<Attribute>
<AttriId>124</AttriId>
<AttriName>EmpresaEmail</AttriName>
<Description>Empresa Email</Description></Attribute>
<Attribute>
<AttriId>129</AttriId>
<AttriName>EmpresaTelefono</AttriName>
<Description>Empresa Telefono</Description></Attribute></AttrisToUpdate></TableToUpdate>
<TableToUpdate>
<Table>
<TableId>26</TableId>
<TableName>Empresa</TableName>
<Description>Empresa</Description></Table>
<TableAction>update</TableAction>
<AttrisToUpdate>
<Attribute>
<AttriId>121</AttriId>
<AttriName>EmpresaNombre</AttriName>
<Description>Empresa Nombre</Description></Attribute>
<Attribute>
<AttriId>122</AttriId>
<AttriName>EmpresaDireccion</AttriName>
<Description>Empresa Direccion</Description></Attribute>
<Attribute>
<AttriId>123</AttriId>
<AttriName>EmpresaRuc</AttriName>
<Description>Empresa Ruc</Description></Attribute>
<Attribute>
<AttriId>124</AttriId>
<AttriName>EmpresaEmail</AttriName>
<Description>Empresa Email</Description></Attribute>
<Attribute>
<AttriId>129</AttriId>
<AttriName>EmpresaTelefono</AttriName>
<Description>Empresa Telefono</Description></Attribute></AttrisToUpdate></TableToUpdate>
<TableToUpdate>
<Table>
<TableId>26</TableId>
<TableName>Empresa</TableName>
<Description>Empresa</Description></Table>
<TableAction>delete</TableAction>
<AttrisToUpdate></AttrisToUpdate></TableToUpdate></TablesToUpdate>
<AfterInsertRules></AfterInsertRules>
<AfterUpdateRules></AfterUpdateRules>
<AfterDeleteRules></AfterDeleteRules>
<TablesToControlOnDelete>
<Table>
<TableId>28</TableId>
<TableName>Factura</TableName>
<Description>Factura</Description>
<RecordsToRead>one</RecordsToRead>
<KeyAttributes>
<Attribute>
<AttriId>28</AttriId>
<AttriName>EmpresaId</AttriName>
<Description>Empresa Id</Description></Attribute></KeyAttributes></Table></TablesToControlOnDelete>
<Levels></Levels>
<AfterTrnRules></AfterTrnRules>
<AfterLevelRules></AfterLevelRules></Level></Levels>
<Suggests></Suggests></ObjectSpec>